{
  "patient": {
    "id": "fixture-09",
    "name": "Test Patient 09 — HFrEF + outside ibuprofen",
    "dob": "1957-11-08",
    "sex": "male"
  },
  "conditions": [
    {
      "code": "I50.22",
      "codeSystem": "http://hl7.org/fhir/sid/icd-10-cm",
      "display": "Chronic systolic (congestive) heart failure",
      "status": "active",
      "onsetDate": "2022-06-19"
    }
  ],
  "medications": [
    {
      "rxnormCode": "1656328",
      "name": "sacubitril/valsartan 49-51 MG Oral Tablet",
      "genericName": "sacubitril/valsartan",
      "dose": "49-51 mg twice daily",
      "route": "oral",
      "status": "active",
      "prescribedDate": "2024-03-12"
    },
    {
      "rxnormCode": "866924",
      "name": "metoprolol succinate 50 MG Extended Release Oral Tablet",
      "genericName": "metoprolol succinate",
      "dose": "50 mg daily",
      "route": "oral",
      "status": "active",
      "prescribedDate": "2024-03-12"
    },
    {
      "rxnormCode": "8629",
      "name": "spironolactone 25 MG Oral Tablet",
      "genericName": "spironolactone",
      "dose": "25 mg daily",
      "route": "oral",
      "status": "active",
      "prescribedDate": "2024-03-12"
    },
    {
      "rxnormCode": "1545664",
      "name": "empagliflozin 10 MG Oral Tablet",
      "genericName": "empagliflozin",
      "dose": "10 mg daily",
      "route": "oral",
      "status": "active",
      "prescribedDate": "2024-03-12"
    },
    {
      "rxnormCode": "5640",
      "name": "ibuprofen 600 MG Oral Tablet",
      "genericName": "ibuprofen",
      "dose": "600 mg three times daily PRN",
      "route": "oral",
      "status": "active",
      "prescribedDate": "2026-05-06"
    }
  ],
  "observations": [
    {
      "loincCode": "10230-1",
      "display": "Left ventricular ejection fraction by 2D echo",
      "value": 32,
      "unit": "%",
      "effectiveDate": "2026-02-04",
      "category": "imaging"
    },
    {
      "loincCode": "33914-3",
      "display": "Glomerular filtration rate/1.73 sq M.predicted",
      "value": 58,
      "unit": "mL/min/1.73m2",
      "effectiveDate": "2026-04-22",
      "category": "laboratory"
    },
    {
      "loincCode": "2823-3",
      "display": "Potassium [Moles/volume] in Serum or Plasma",
      "value": 4.4,
      "unit": "mEq/L",
      "effectiveDate": "2026-04-22",
      "category": "laboratory"
    }
  ],
  "allergies": []
}
